MANIFEST.in
README.rst
setup.py
pysqlw/__init__.py
pysqlw/mysqlw.py
pysqlw/pysqlw.py
pysqlw/sqlitew.py
pysqlw/sqltype.py
pysqlw.egg-info/PKG-INFO
pysqlw.egg-info/SOURCES.txt
pysqlw.egg-info/dependency_links.txt
pysqlw.egg-info/not-zip-safe
pysqlw.egg-info/top_level.txt