Metadata-Version: 1.1
Name: pysqlw
Version: 1.2.1
Summary: Python wrapper to make interacting with SQL databases easy
Home-page: https://github.com/plausibility/pysqlw
Author: plausibility
Author-email: chris@gibsonsec.org
License: MIT
Keywords: sql sqlite mysql wrapper
Platform: UNKNOWN
Classifier: Development Status :: 5 - Production/Stable
Classifier: Intended Audience :: Developers
Classifier: License :: OSI Approved :: MIT License
Classifier: Operating System :: OS Independent
Classifier: Programming Language :: Python :: 2
Classifier: Topic :: Database
